weathervault/__init__.py
weathervault/_constants.py
weathervault/_parsing.py
weathervault/_registry.py
weathervault/stations.py
weathervault/weather.py
weathervault/data/__init__.py
weathervault-0.2.0.dist-info/licenses/LICENSE
weathervault-0.2.0.dist-info/METADATA
weathervault-0.2.0.dist-info/WHEEL
weathervault-0.2.0.dist-info/top_level.txt
weathervault-0.2.0.dist-info/RECORD
