Metadata-Version: 2.4
Name: weathervault
Version: 0.2.0
Summary: Obtain Polars DataFrames of historical weather data from the NCEI weather database
Author-email: Rich Iannone <riannone@me.com>
Maintainer-email: Rich Iannone <riannone@me.com>
License: MIT License
Project-URL: Homepage, https://github.com/rich-iannone/weathervault
Project-URL: Repository, https://github.com/rich-iannone/weathervault
Project-URL: Bug Tracker, https://github.com/rich-iannone/gweathervault/issues
Keywords: weather,meteorology,climate,ncei,noaa,isd,polars,data
Classifier: Development Status :: 3 - Alpha
Classifier: Intended Audience :: Science/Research
Classifier: License :: OSI Approved :: MIT License
Classifier: Operating System :: OS Independent
Classifier: Programming Language :: Python :: 3
Classifier: Programming Language :: Python :: 3.10
Classifier: Programming Language :: Python :: 3.11
Classifier: Programming Language :: Python :: 3.12
Classifier: Programming Language :: Python :: 3.13
Classifier: Topic :: Scientific/Engineering :: Atmospheric Science
Requires-Python: >=3.10
License-File: LICENSE
Requires-Dist: polars>=1.0.0
Requires-Dist: httpx>=0.27.0
Requires-Dist: timezonefinder>=6.5.0
Requires-Dist: importlib-metadata
Requires-Dist: tzdata>=2023.3; sys_platform == "win32"
Provides-Extra: dev
Requires-Dist: pytest>=8.0.0; extra == "dev"
Requires-Dist: pytest-cov>=4.0.0; extra == "dev"
Requires-Dist: pytest-timeout>=2.0.0; extra == "dev"
Requires-Dist: ruff>=0.4.0; extra == "dev"
Dynamic: license-file
